entropy_password_generator/__init__.py
entropy_password_generator/password_generator.py
entropy_password_generator/screenshots/--length85.png
entropy_password_generator/screenshots/--mode15.png
entropy_password_generator-0.6.4.dist-info/METADATA
entropy_password_generator-0.6.4.dist-info/WHEEL
entropy_password_generator-0.6.4.dist-info/entry_points.txt
entropy_password_generator-0.6.4.dist-info/licenses/LICENSE.md
entropy_password_generator-0.6.4.dist-info/RECORD
