Metadata-Version: 2.4
Name: entropy-password-generator
Version: 0.6.4
Summary: A secure password generator with high entropy, compliant with Proton and NIST standards
Project-URL: Homepage, https://github.com/gerivanc/entropy-password-generator
Project-URL: Repository, https://github.com/gerivanc/entropy-password-generator.git
Project-URL: Issues, https://github.com/gerivanc/entropy-password-generator/issues
Project-URL: Changelog, https://github.com/gerivanc/entropy-password-generator/blob/main/CHANGELOG.md
Author-email: Gerivan Costa dos Santos <dean-grumbly-plop@duck.com>
License: MIT
License-File: LICENSE.md
Keywords: cryptography,entropy,generator,password,password-manager,security
Classifier: License :: OSI Approved :: MIT License
Classifier: Operating System :: OS Independent
Classifier: Programming Language :: Python :: 3
Classifier: Programming Language :: Python :: 3.8
Classifier: Programming Language :: Python :: 3.9
Classifier: Programming Language :: Python :: 3.10
Classifier: Programming Language :: Python :: 3.11
Classifier: Programming Language :: Python :: 3.12
Requires-Python: >=3.8
Requires-Dist: toml
